examples/__init__.py
examples/firmware_update_example.py
examples/firmware_update_loop.py
examples/simple_example.py
examples/trajectory_logger_example.py
mecademicpy/__init__.py
mecademicpy/_robot_base.py
mecademicpy/_robot_trajectory_logger.py
mecademicpy/mx_robot_def.py
mecademicpy/mx_robot_def_legacy.py
mecademicpy/robot.py
mecademicpy/robot_classes.py
mecademicpy/robot_global_functions.py
mecademicpy/robot_initializer.py
mecademicpy/robot_sidecar_classes.py
mecademicpy/robot_trajectory_files.py
mecademicpy/tools.py
mecademicpy-2.3.0.dist-info/licenses/LICENSE
tests/__init__.py
tests/robot_test.py
tests/robot_trajectory_files_test.py
mecademicpy-2.3.0.dist-info/METADATA
mecademicpy-2.3.0.dist-info/WHEEL
mecademicpy-2.3.0.dist-info/top_level.txt
mecademicpy-2.3.0.dist-info/RECORD
