Metadata-Version: 2.4
Name: mecademicpy
Version: 2.3.0
Summary: A package to control the Mecademic robots through python
Home-page: https://github.com/Mecademic/mecademicpy
Author: Mecademic
Author-email: support@mecademic.com
License: MIT
Classifier: Programming Language :: Python :: 3
Classifier: License :: OSI Approved :: MIT License
Classifier: Operating System :: OS Independent
Requires-Python: >=3.7
License-File: LICENSE
Requires-Dist: dataclasses_json>=0.5.4
Requires-Dist: deprecation
Requires-Dist: pandas
Requires-Dist: requests
Requires-Dist: pyyaml
Dynamic: author
Dynamic: author-email
Dynamic: classifier
Dynamic: description
Dynamic: description-content-type
Dynamic: home-page
Dynamic: license
Dynamic: license-file
Dynamic: requires-dist
Dynamic: requires-python
Dynamic: summary
